rdf2dot/__init__.py
rdf2dot/rdf2dot.py
rdf2dot-0.1.5.dist-info/COPYING
rdf2dot-0.1.5.dist-info/METADATA
rdf2dot-0.1.5.dist-info/WHEEL
rdf2dot-0.1.5.dist-info/entry_points.txt
rdf2dot-0.1.5.dist-info/top_level.txt
rdf2dot-0.1.5.dist-info/RECORD
