Metadata-Version: 2.1
Name: rdf2dot
Version: 0.1.5
Summary: rdf2dot
Home-page: https://odahub.io/
Author: V.S.
Author-email: vladimir.savchenko@gmail.com
License: GPL-2+
Platform: UNKNOWN
Classifier: Development Status :: 4 - Beta
Classifier: Environment :: Console
Classifier: Intended Audience :: Science/Research
Classifier: License :: OSI Approved :: GNU General Public License v2 or later (GPLv2+)
Classifier: Operating System :: POSIX
Classifier: Programming Language :: Python :: 2.7
Classifier: Programming Language :: Python :: 3.4
Classifier: Programming Language :: Python :: 3.5
Classifier: Programming Language :: Python :: 3.6
Classifier: Programming Language :: Python :: 3.7
Classifier: Topic :: Internet
Classifier: Topic :: Scientific/Engineering :: Astronomy
License-File: COPYING
Requires-Dist: path.py
Requires-Dist: click
Requires-Dist: pyyaml
